deepctl_cmd_mcp/__init__.py
deepctl_cmd_mcp/__main__.py
deepctl_cmd_mcp/command.py
deepctl_cmd_mcp/gnosis.py
deepctl_cmd_mcp/models.py
deepctl_cmd_mcp-0.1.10.dist-info/METADATA
deepctl_cmd_mcp-0.1.10.dist-info/WHEEL
deepctl_cmd_mcp-0.1.10.dist-info/entry_points.txt
deepctl_cmd_mcp-0.1.10.dist-info/top_level.txt
deepctl_cmd_mcp-0.1.10.dist-info/RECORD
