Metadata-Version: 2.4
Name: deepctl-cmd-mcp
Version: 0.1.10
Summary: MCP server command for deepctl to interact with Deepgram's AI assistant service
Author-email: Deepgram <devrel@deepgram.com>
License-Expression: MIT
Requires-Python: >=3.10
Requires-Dist: deepctl-core>=0.1.10
Requires-Dist: mcp>=1.0.0
Requires-Dist: rich>=13.9.4
Requires-Dist: click>=8.1.7
Requires-Dist: pydantic>=2.10.1
Requires-Dist: httpx>=0.28.1
Provides-Extra: dev
Requires-Dist: pytest>=8.3.3; extra == "dev"
Requires-Dist: pytest-asyncio>=0.24.0; extra == "dev"
Requires-Dist: pytest-cov>=6.0.0; extra == "dev"
Requires-Dist: pytest-mock>=3.14.0; extra == "dev"
Requires-Dist: mypy>=1.13.0; extra == "dev"
Requires-Dist: ruff>=0.8.1; extra == "dev"
